tinylogger/__init__.py
tinylogger/log.py
tinylogger-1.0.0.dist-info/LICENSE
tinylogger-1.0.0.dist-info/METADATA
tinylogger-1.0.0.dist-info/WHEEL
tinylogger-1.0.0.dist-info/top_level.txt
tinylogger-1.0.0.dist-info/RECORD
