Metadata-Version: 2.1
Name: tinylogger
Version: 1.0.0
Summary: An easy use and more powerful android style logging util
Home-page: https://github.com/frankzhangv5/tinylogger-dist
Author: frank.zhang
Author-email: frankzhang02010@gmail.com
License: LICENSE
Platform: UNKNOWN
Classifier: Programming Language :: Python :: 3
Classifier: License :: OSI Approved :: MIT License
Classifier: Operating System :: OS Independent
